qpass/__init__.py
qpass/cli.py
qpass/exceptions.py
qpass/tests.py
qpass-2.3.dist-info/METADATA
qpass-2.3.dist-info/RECORD
qpass-2.3.dist-info/WHEEL
qpass-2.3.dist-info/entry_points.txt
qpass-2.3.dist-info/top_level.txt
