Metadata-Version: 2.1
Name: qpass
Version: 2.3
Summary: Frontend for pass (the standard unix password manager)
Home-page: https://github.com/xolox/python-qpass
Author: Peter Odding
Author-email: peter@peterodding.com
License: MIT
Platform: UNKNOWN
Classifier: Development Status :: 4 - Beta
Classifier: Environment :: Console
Classifier: Environment :: MacOS X
Classifier: Intended Audience :: Developers
Classifier: Intended Audience :: Information Technology
Classifier: Intended Audience :: System Administrators
Classifier: License :: OSI Approved :: MIT License
Classifier: Natural Language :: English
Classifier: Operating System :: MacOS
Classifier: Operating System :: POSIX :: Linux
Classifier: Programming Language :: Python
Classifier: Programming Language :: Python :: 2
Classifier: Programming Language :: Python :: 2.6
Classifier: Programming Language :: Python :: 2.7
Classifier: Programming Language :: Python :: 3
Classifier: Programming Language :: Python :: 3.4
Classifier: Programming Language :: Python :: 3.5
Classifier: Programming Language :: Python :: 3.6
Classifier: Programming Language :: Python :: Implementation :: CPython
Classifier: Programming Language :: Python :: Implementation :: PyPy
Classifier: Topic :: Security
Classifier: Topic :: Security :: Cryptography
Classifier: Topic :: Software Development
Classifier: Topic :: Software Development :: Libraries
Classifier: Topic :: Software Development :: Libraries :: Python Modules
Classifier: Topic :: System
Classifier: Topic :: System :: Systems Administration
Classifier: Topic :: Terminals
Classifier: Topic :: Utilities
Requires-Dist: coloredlogs (>=6.1)
Requires-Dist: executor (>=17.1)
Requires-Dist: humanfriendly (>=4.8)
Requires-Dist: naturalsort (>=1.5.1)
Requires-Dist: proc (>=0.15)
Requires-Dist: property-manager (>=2.0)
Requires-Dist: verboselogs (>=1.6)
